Workbook

Sheet Read me
A1: Hospital Appointment & Patient Management System
A2: User story backlog and sprint plan · Advanced Python major assignment · Due 21 October 2026
A5: How to use this file
A6: 1 | B6: Open the 'User Stories' sheet. Every row is one story with its acceptance criteria.
A7: 2 | B7: Fill only the yellow columns: Points, Owner, Sprint, Status. They have drop-down lists.
A8: 3 | B8: The 'Sprint Plan' sheet adds everything up by itself. Do not type into its white cells.
A9: 4 | B9: Update Status at the end of each working session so the progress figures stay true.
A11: Story points
A12: 1 | B12: Trivial, under an hour
A13: 2 | B13: Small, half a day
A14: 3 | B14: Normal, about one day
A15: 5 | B15: Large, two days, worth splitting if possible
A16: 8 | B16: Very large, needs design first
A18: Priority (MoSCoW)
A19: Must | B19: Tier 1 and 2 in the PRD. The project fails without it.
A20: Should | B20: Valuable but the demo survives without it.
A21: Could | B21: Tier 3 bonus. Build only if ahead of schedule; otherwise write it up as a future enhancement.
A23: Rule
A24: Code freeze | B24: 16 October. After that date no new story is started; only bug fixes, report and slides.

Sheet User Stories
A1: Product backlog
A2: Yellow columns are yours to fill in. Everything else is set by the PRD.
A4: Story ID | B4: Epic | C4: As a... | D4: I want... | E4: So that... | F4: Acceptance criteria | G4: PRD ref | H4: Priority | I4: Points | J4: Owner | K4: Sprint | L4: Status
A5: US-01 | B5: Foundation | C5: developer | D5: a shared Git repo with the folder structure and schema.sql | E5: everyone can start coding without overwriting each other | F5: Repo cloned by all 4; running schema.sql creates 10 tables with no error | G5: — | H5: Must | I5: 3 | J5: Person 1 | K5: Sprint 1 | L5: Not started
A6: US-02 | B6: Foundation | C6: developer | D6: a database module that opens the connection and creates tables | E6: every other module has one way to reach the data | F6: init_db() is safe to run twice; foreign keys are ON | G6: — | H6: Must | I6: 2 | J6: Person 1 | K6: Sprint 1 | L6: Not started
A7: US-03 | B7: Foundation | C7: developer | D7: the model classes Person, Patient, Doctor and Appointment | E7: the team shares one definition of every object | F7: Patient and Doctor inherit Person and override display_info(); age has a validating setter | G7: — | H7: Must | I7: 5 | J7: Person 1 | K7: Sprint 1 | L7: Not started
A8: US-04 | B8: Foundation | C8: developer | D8: reusable input helpers for text, numbers, phone, date and time | E8: no menu ever crashes on bad typing | F8: Letters typed into a number field re-prompt instead of raising | G8: — | H8: Must | I8: 3 | J8: Person 2 | K8: Sprint 1 | L8: Not started
A9: US-05 | B9: Foundation | C9: developer | D9: a seed script that fills the database with demo data | E9: we can test and demo without typing records by hand | F9: 3 departments, 6 doctors, 20 patients, 30 appointments created by one command | G9: — | H9: Must | I9: 3 | J9: Person 2 | K9: Sprint 1 | L9: Not started
A10: US-06 | B10: Authentication | C10: staff member | D10: to log in with a username and password | E10: patient data is not open to anyone who opens the program | F10: Correct login opens the menu; 3 wrong attempts exit; passwords stored as SHA-256 | G10: FR-1.1 | H10: Must | I10: 3 | J10: Person 1 | K10: Sprint 1 | L10: Not started
A11: US-07 | B11: Authentication | C11: user | D11: to see only the menu options my role allows | E11: staff cannot reach functions they should not use | F11: Receptionist login shows no admin options; doctor login shows only their own appointments | G11: FR-1.2 | H11: Must | I11: 3 | J11: Person 1 | K11: Sprint 1 | L11: Not started
A12: US-08 | B12: Authentication | C12: admin | D12: to create, deactivate and reset user accounts | E12: staff changes do not need a developer | F12: New account can log in; deactivated account is refused | G12: FR-1.3 | H12: Should | I12: 3 | J12: Person 1 | K12: Sprint 2 | L12: Not started
A13: US-09 | B13: Patients | C13: receptionist | D13: to register a new patient with an auto-generated ID | E13: each patient is identified once and never duplicated | F13: ID follows P001, P002; name and phone are required; created_at is stored | G13: FR-2.1 | H13: Must | I13: 3 | J13: Person 2 | K13: Sprint 2 | L13: Not started
A14: US-10 | B14: Patients | C14: receptionist | D14: to update a patient's details | E14: records stay correct when a phone number or address changes | F14: Any field except the ID can be changed; validation runs again on the new value | G14: FR-2.2 | H14: Must | I14: 2 | J14: Person 2 | K14: Sprint 2 | L14: Not started
A15: US-11 | B15: Patients | C15: receptionist | D15: to search patients by ID, part of the name, or phone | E15: I can find a returning patient in seconds | F15: Partial name matches; no match prints a message, not an error | G15: FR-2.3 | H15: Must | I15: 3 | J15: Person 2 | K15: Sprint 2 | L15: Not started
A16: US-12 | B16: Patients | C16: receptionist | D16: to list all patients in a formatted table | E16: I can see the register at a glance | F16: Columns aligned; long lists paged 20 at a time | G16: FR-2.4 | H16: Must | I16: 2 | J16: Person 2 | K16: Sprint 2 | L16: Not started
... A47: US-43 | B47: Delivery | C47: team | D47: 10 to 15 slides and a rehearsed live demo | E47: the presentation runs without surprises | F47: Demo rehearsed twice on seeded data; every member can answer on their own module | G47: — | H47: Must | I47: 5 | J47: All | K47: Sprint 4 | L47: Not started
H49: Total points | I49: =SUM(I5:I47) -> 137
H50: Done points | I50: =SUMIF(L5:L47,"Done",I5:I47) -> 0
H51: Complete | I51: =IFERROR(I50/I49,0) -> 0

Sheet Sprint Plan
A1: Sprint plan
A2: Five weeks, four people. Planned, done and remaining points are calculated from the User Stories sheet.
A4: Sprint | B4: Goal | C4: Start | D4: End | E4: Weeks | F4: Capacity (pts) | G4: Planned (pts) | H4: Done (pts) | I4: Remaining | J4: % complete | K4: Load vs capacity
A5: Sprint 1 | B5: Foundation: database, classes, login, menu skeleton | C5: 28 Sep | D5: 4 Oct | E5: 1 | F5: 40 | G5: =SUMIF('User Stories'!$K$5:$K$47,$A5,'User Stories'!$I$5:$I$47) -> 22 | H5: =SUMIFS('User Stories'!$I$5:$I$47,'User Stories'!$K$5:$K$47,$A5,'User Stories'!$L$5:$L$47,"Done") -> 0 | I5: =G5-H5 -> 22 | J5: =IFERROR(H5/G5,0) -> 0 | K5: =IFERROR(G5/F5,0) -> 0.55
A6: Sprint 2 | B6: Core records: patients, doctors, departments, first bookings | C6: 5 Oct | D6: 11 Oct | E6: 1 | F6: 40 | G6: =SUMIF('User Stories'!$K$5:$K$47,$A6,'User Stories'!$I$5:$I$47) -> 32 | H6: =SUMIFS('User Stories'!$I$5:$I$47,'User Stories'!$K$5:$K$47,$A6,'User Stories'!$L$5:$L$47,"Done") -> 0 | I6: =G6-H6 -> 32 | J6: =IFERROR(H6/G6,0) -> 0 | K6: =IFERROR(G6/F6,0) -> 0.8
A7: Sprint 3 | B7: Appointments, schedules, billing and records | C7: 12 Oct | D7: 16 Oct | E7: 2 | F7: 40 | G7: =SUMIF('User Stories'!$K$5:$K$47,$A7,'User Stories'!$I$5:$I$47) -> 43 | H7: =SUMIFS('User Stories'!$I$5:$I$47,'User Stories'!$K$5:$K$47,$A7,'User Stories'!$L$5:$L$47,"Done") -> 0 | I7: =G7-H7 -> 43 | J7: =IFERROR(H7/G7,0) -> 0 | K7: =IFERROR(G7/F7,0) -> 1.075
A8: Sprint 4 | B8: Bonus features, testing, report, slides, submission | C8: 17 Oct | D8: 21 Oct | E8: 3 | F8: 40 | G8: =SUMIF('User Stories'!$K$5:$K$47,$A8,'User Stories'!$I$5:$I$47) -> 40 | H8: =SUMIFS('User Stories'!$I$5:$I$47,'User Stories'!$K$5:$K$47,$A8,'User Stories'!$L$5:$L$47,"Done") -> 0 | I8: =G8-H8 -> 40 | J8: =IFERROR(H8/G8,0) -> 0 | K8: =IFERROR(G8/F8,0) -> 1
A9: Total | F9: =SUM(F5:F8) -> 160 | G9: =SUM(G5:G8) -> 137 | H9: =SUM(H5:H8) -> 0 | I9: =SUM(I5:I8) -> 137 | J9: =IFERROR(H9/G9,0) -> 0
A12: Points per person per sprint
A13: Person | B13: Sprint 1 | C13: Sprint 2 | D13: Sprint 3 | E13: Sprint 4 | F13: Total
A14: Person 1 | B14: =SUMIFS('User Stories'!$I$5:$I$47,'User Stories'!$J$5:$J$47,$A14,'User Stories'!$K$5:$K$47,B$13) -> 16 | C14: =SUMIFS('User Stories'!$I$5:$I$47,'User Stories'!$J$5:$J$47,$A14,'User Stories'!$K$5:$K$47,C$13) -> 3 | D14: =SUMIFS('User Stories'!$I$5:$I$47,'User Stories'!$J$5:$J$47,$A14,'User Stories'!$K$5:$K$47,D$13) -> 3 | E14: =SUMIFS('User Stories'!$I$5:$I$47,'User Stories'!$J$5:$J$47,$A14,'User Stories'!$K$5:$K$47,E$13) -> 5 | F14: =SUM(B14:E14) -> 27
A15: Person 2 | B15: =SUMIFS('User Stories'!$I$5:$I$47,'User Stories'!$J$5:$J$47,$A15,'User Stories'!$K$5:$K$47,B$13) -> 6 | C15: =SUMIFS('User Stories'!$I$5:$I$47,'User Stories'!$J$5:$J$47,$A15,'User Stories'!$K$5:$K$47,C$13) -> 12 | D15: =SUMIFS('User Stories'!$I$5:$I$47,'User Stories'!$J$5:$J$47,$A15,'User Stories'!$K$5:$K$47,D$13) -> 3 | E15: =SUMIFS('User Stories'!$I$5:$I$47,'User Stories'!$J$5:$J$47,$A15,'User Stories'!$K$5:$K$47,E$13) -> 0 | F15: =SUM(B15:E15) -> 21
A16: Person 3 | B16: =SUMIFS('User Stories'!$I$5:$I$47,'User Stories'!$J$5:$J$47,$A16,'User Stories'!$K$5:$K$47,B$13) -> 0 | C16: =SUMIFS('User Stories'!$I$5:$I$47,'User Stories'!$J$5:$J$47,$A16,'User Stories'!$K$5:$K$47,C$13) -> 9 | D16: =SUMIFS('User Stories'!$I$5:$I$47,'User Stories'!$J$5:$J$47,$A16,'User Stories'!$K$5:$K$47,D$13) -> 13 | E16: =SUMIFS('User Stories'!$I$5:$I$47,'User Stories'!$J$5:$J$47,$A16,'User Stories'!$K$5:$K$47,E$13) -> 6 | F16: =SUM(B16:E16) -> 28
A17: Person 4 | B17: =SUMIFS('User Stories'!$I$5:$I$47,'User Stories'!$J$5:$J$47,$A17,'User Stories'!$K$5:$K$47,B$13) -> 0 | C17: =SUMIFS('User Stories'!$I$5:$I$47,'User Stories'!$J$5:$J$47,$A17,'User Stories'!$K$5:$K$47,C$13) -> 8 | D17: =SUMIFS('User Stories'!$I$5:$I$47,'User Stories'!$J$5:$J$47,$A17,'User Stories'!$K$5:$K$47,D$13) -> 24 | E17: =SUMIFS('User Stories'!$I$5:$I$47,'User Stories'!$J$5:$J$47,$A17,'User Stories'!$K$5:$K$47,E$13) -> 11 | F17: =SUM(B17:E17) -> 43
A18: All | B18: =SUMIFS('User Stories'!$I$5:$I$47,'User Stories'!$J$5:$J$47,$A18,'User Stories'!$K$5:$K$47,B$13) -> 0 | C18: =SUMIFS('User Stories'!$I$5:$I$47,'User Stories'!$J$5:$J$47,$A18,'User Stories'!$K$5:$K$47,C$13) -> 0 | D18: =SUMIFS('User Stories'!$I$5:$I$47,'User Stories'!$J$5:$J$47,$A18,'User Stories'!$K$5:$K$47,D$13) -> 0 | E18: =SUMIFS('User Stories'!$I$5:$I$47,'User Stories'!$J$5:$J$47,$A18,'User Stories'!$K$5:$K$47,E$13) -> 18 | F18: =SUM(B18:E18) -> 18
A20: Capacity is an estimate: 4 people x about 10 points a week. Change the yellow cells once you know your real pace.
A21: Load above 100% means the sprint is overbooked: move a Could story to a later sprint or drop it.
